odoo8_addon_project_closing-8.0.0.1.1.99.dev10-py2.7-nspkg.pth
odoo8_addon_project_closing-8.0.0.1.1.99.dev10.dist-info/METADATA
odoo8_addon_project_closing-8.0.0.1.1.99.dev10.dist-info/RECORD
odoo8_addon_project_closing-8.0.0.1.1.99.dev10.dist-info/WHEEL
odoo8_addon_project_closing-8.0.0.1.1.99.dev10.dist-info/namespace_packages.txt
odoo8_addon_project_closing-8.0.0.1.1.99.dev10.dist-info/top_level.txt
odoo_addons/project_closing/README.rst
odoo_addons/project_closing/__init__.py
odoo_addons/project_closing/__openerp__.py
odoo_addons/project_closing/project.py
odoo_addons/project_closing/i18n/de.po
odoo_addons/project_closing/i18n/es.po
odoo_addons/project_closing/i18n/es_MX.po
odoo_addons/project_closing/i18n/fi.po
odoo_addons/project_closing/i18n/fr.po
odoo_addons/project_closing/i18n/hr.po
odoo_addons/project_closing/i18n/project_closing.pot
odoo_addons/project_closing/i18n/pt.po
odoo_addons/project_closing/i18n/pt_BR.po
odoo_addons/project_closing/i18n/pt_PT.po
odoo_addons/project_closing/i18n/sl.po
odoo_addons/project_closing/i18n/zh_CN.po
odoo_addons/project_closing/static/description/icon.png
